[ { "gid": "article", "ns": "http://docbook.org/ns/docbook", "pattern": "hcontainer", "text": 17656, "before": 0, "parent": 0, "depth": 0, "xmlId": "e0" , "children": [{ "gid": "title", "ns": "http://docbook.org/ns/docbook", "pattern": "block", "text": 48, "before": 0, "parent": 17656, "depth": 1, "xmlId": "e1" , "children": [{ "pattern": "textual", "text": 48, "before": 0, "parent": 48, "depth": 2, "xmlId": "e1" } ] }, { "gid": "info", "ns": "http://docbook.org/ns/docbook", "pattern": "record", "text": 3524, "before": 48, "parent": 17656, "depth": 1, "xmlId": "e2" , "children": [{ "gid": "confgroup", "ns": "http://docbook.org/ns/docbook", "pattern": "record", "text": 55, "before": 48, "parent": 3524, "depth": 2, "xmlId": "e3" , "children": [{ "gid": "conftitle", "ns": "http://docbook.org/ns/docbook", "pattern": "field", "text": 36, "before": 48, "parent": 55, "depth": 3, "xmlId": "e4" , "children": [{ "pattern": "textual", "text": 36, "before": 48, "parent": 36, "depth": 4, "xmlId": "e4" } ] }, { "gid": "confdates", "ns": "http://docbook.org/ns/docbook", "pattern": "field", "text": 19, "before": 84, "parent": 55, "depth": 3, "xmlId": "e5" , "children": [{ "pattern": "textual", "text": 19, "before": 84, "parent": 19, "depth": 4, "xmlId": "e5" } ] } ] }, { "gid": "abstract", "ns": "http://docbook.org/ns/docbook", "pattern": "container", "text": 145, "before": 103, "parent": 3524, "depth": 2, "xmlId": "e6" , "children": [{ "gid": "para", "ns": "http://docbook.org/ns/docbook", "pattern": "block", "text": 145, "before": 103, "parent": 145, "depth": 3, "xmlId": "e7" , "children": [{ "pattern": "textual", "text": 145, "before": 103, "parent": 145, "depth": 4, "xmlId": "e7" } ] } ] }, { "gid": "author", "ns": "http://docbook.org/ns/docbook", "pattern": "record", "text": 1102, "before": 248, "parent": 3524, "depth": 2, "xmlId": "e8" , "children": [{ "gid": "personname", "ns": "http://docbook.org/ns/docbook", "pattern": "record", "text": 15, "before": 248, "parent": 1102, "depth": 3, "xmlId": "e9" , "children": [{ "gid": "firstname", "ns": "http://docbook.org/ns/docbook", "pattern": "field", "text": 4, "before": 248, "parent": 15, "depth": 4, "xmlId": "e10" , "children": [{ "pattern": "textual", "text": 4, "before": 248, "parent": 4, "depth": 5, "xmlId": "e10" } ] }, { "gid": "surname", "ns": "http://docbook.org/ns/docbook", "pattern": "field", "text": 11, "before": 252, "parent": 15, "depth": 4, "xmlId": "e11" , "children": [{ "pattern": "textual", "text": 11, "before": 252, "parent": 11, "depth": 5, "xmlId": "e11" } ] } ] }, { "gid": "personblurb", "ns": "http://docbook.org/ns/docbook", "pattern": "container", "text": 988, "before": 263, "parent": 1102, "depth": 3, "xmlId": "e12" , "children": [{ "gid": "para", "ns": "http://docbook.org/ns/docbook", "pattern": "block", "text": 847, "before": 263, "parent": 988, "depth": 4, "xmlId": "e13" , "children": [{ "pattern": "textual", "text": 847, "before": 263, "parent": 847, "depth": 5, "xmlId": "e13" } ] }, { "gid": "para", "ns": "http://docbook.org/ns/docbook", "pattern": "block", "text": 141, "before": 1110, "parent": 988, "depth": 4, "xmlId": "e14" , "children": [{ "pattern": "textual", "text": 141, "before": 1110, "parent": 141, "depth": 5, "xmlId": "e14" } ] } ] }, { "gid": "affiliation", "ns": "http://docbook.org/ns/docbook", "pattern": "record", "text": 44, "before": 1251, "parent": 1102, "depth": 3, "xmlId": "e15" , "children": [{ "gid": "orgname", "ns": "http://docbook.org/ns/docbook", "pattern": "block", "text": 44, "before": 1251, "parent": 44, "depth": 4, "xmlId": "e16" , "children": [{ "pattern": "textual", "text": 44, "before": 1251, "parent": 44, "depth": 5, "xmlId": "e16" } ] } ] }, { "gid": "affiliation", "ns": "http://docbook.org/ns/docbook", "pattern": "record", "text": 21, "before": 1295, "parent": 1102, "depth": 3, "xmlId": "e17" , "children": [{ "gid": "orgname", "ns": "http://docbook.org/ns/docbook", "pattern": "block", "text": 21, "before": 1295, "parent": 21, "depth": 4, "xmlId": "e18" , "children": [{ "pattern": "textual", "text": 21, "before": 1295, "parent": 21, "depth": 5, "xmlId": "e18" } ] } ] }, { "gid": "email", "ns": "http://docbook.org/ns/docbook", "pattern": "field", "text": 34, "before": 1316, "parent": 1102, "depth": 3, "xmlId": "e19" , "children": [{ "pattern": "textual", "text": 34, "before": 1316, "parent": 34, "depth": 4, "xmlId": "e19" } ] } ] }, { "gid": "author", "ns": "http://docbook.org/ns/docbook", "pattern": "record", "text": 747, "before": 1350, "parent": 3524, "depth": 2, "xmlId": "e20" , "children": [{ "gid": "personname", "ns": "http://docbook.org/ns/docbook", "pattern": "record", "text": 16, "before": 1350, "parent": 747, "depth": 3, "xmlId": "e21" , "children": [{ "gid": "firstname", "ns": "http://docbook.org/ns/docbook", "pattern": "field", "text": 6, "before": 1350, "parent": 16, "depth": 4, "xmlId": "e22" , "children": [{ "pattern": "textual", "text": 6, "before": 1350, "parent": 6, "depth": 5, "xmlId": "e22" } ] }, { "gid": "surname", "ns": "http://docbook.org/ns/docbook", "pattern": "field", "text": 10, "before": 1356, "parent": 16, "depth": 4, "xmlId": "e23" , "children": [{ "pattern": "textual", "text": 10, "before": 1356, "parent": 10, "depth": 5, "xmlId": "e23" } ] } ] }, { "gid": "personblurb", "ns": "http://docbook.org/ns/docbook", "pattern": "container", "text": 661, "before": 1366, "parent": 747, "depth": 3, "xmlId": "e24" , "children": [{ "gid": "para", "ns": "http://docbook.org/ns/docbook", "pattern": "block", "text": 661, "before": 1366, "parent": 661, "depth": 4, "xmlId": "e25" , "children": [{ "pattern": "textual", "text": 661, "before": 1366, "parent": 661, "depth": 5, "xmlId": "e25" } ] } ] }, { "gid": "affiliation", "ns": "http://docbook.org/ns/docbook", "pattern": "record", "text": 44, "before": 2027, "parent": 747, "depth": 3, "xmlId": "e26" , "children": [{ "gid": "orgname", "ns": "http://docbook.org/ns/docbook", "pattern": "block", "text": 44, "before": 2027, "parent": 44, "depth": 4, "xmlId": "e27" , "children": [{ "pattern": "textual", "text": 44, "before": 2027, "parent": 44, "depth": 5, "xmlId": "e27" } ] } ] }, { "gid": "email", "ns": "http://docbook.org/ns/docbook", "pattern": "field", "text": 26, "before": 2071, "parent": 747, "depth": 3, "xmlId": "e28" , "children": [{ "pattern": "textual", "text": 26, "before": 2071, "parent": 26, "depth": 4, "xmlId": "e28" } ] } ] }, { "gid": "author", "ns": "http://docbook.org/ns/docbook", "pattern": "record", "text": 1421, "before": 2097, "parent": 3524, "depth": 2, "xmlId": "e29" , "children": [{ "gid": "personname", "ns": "http://docbook.org/ns/docbook", "pattern": "record", "text": 11, "before": 2097, "parent": 1421, "depth": 3, "xmlId": "e30" , "children": [{ "gid": "firstname", "ns": "http://docbook.org/ns/docbook", "pattern": "field", "text": 7, "before": 2097, "parent": 11, "depth": 4, "xmlId": "e31" , "children": [{ "pattern": "textual", "text": 7, "before": 2097, "parent": 7, "depth": 5, "xmlId": "e31" } ] }, { "gid": "surname", "ns": "http://docbook.org/ns/docbook", "pattern": "field", "text": 4, "before": 2104, "parent": 11, "depth": 4, "xmlId": "e32" , "children": [{ "pattern": "textual", "text": 4, "before": 2104, "parent": 4, "depth": 5, "xmlId": "e32" } ] } ] }, { "gid": "personblurb", "ns": "http://docbook.org/ns/docbook", "pattern": "container", "text": 1346, "before": 2108, "parent": 1421, "depth": 3, "xmlId": "e33" , "children": [{ "gid": "para", "ns": "http://docbook.org/ns/docbook", "pattern": "block", "text": 1346, "before": 2108, "parent": 1346, "depth": 4, "xmlId": "e34" , "children": [{ "pattern": "textual", "text": 1346, "before": 2108, "parent": 1346, "depth": 5, "xmlId": "e34" } ] } ] }, { "gid": "affiliation", "ns": "http://docbook.org/ns/docbook", "pattern": "record", "text": 44, "before": 3454, "parent": 1421, "depth": 3, "xmlId": "e35" , "children": [{ "gid": "orgname", "ns": "http://docbook.org/ns/docbook", "pattern": "block", "text": 44, "before": 3454, "parent": 44, "depth": 4, "xmlId": "e36" , "children": [{ "pattern": "textual", "text": 44, "before": 3454, "parent": 44, "depth": 5, "xmlId": "e36" } ] } ] }, { "gid": "email", "ns": "http://docbook.org/ns/docbook", "pattern": "field", "text": 20, "before": 3498, "parent": 1421, "depth": 3, "xmlId": "e37" , "children": [{ "pattern": "textual", "text": 20, "before": 3498, "parent": 20, "depth": 4, "xmlId": "e37" } ] } ] }, { "gid": "legalnotice", "ns": "http://docbook.org/ns/docbook", "pattern": "container", "text": 54, "before": 3518, "parent": 3524, "depth": 2, "xmlId": "e38" , "children": [{ "gid": "para", "ns": "http://docbook.org/ns/docbook", "pattern": "block", "text": 54, "before": 3518, "parent": 54, "depth": 3, "xmlId": "e39" , "children": [{ "pattern": "textual", "text": 54, "before": 3518, "parent": 54, "depth": 4, "xmlId": "e39" } ] } ] } ] }, { "gid": "section", "ns": "http://docbook.org/ns/docbook", "pattern": "hcontainer", "text": 796, "before": 3572, "parent": 17656, "depth": 1, "xmlId": "e40" , "children": [{ "gid": "title", "ns": "http://docbook.org/ns/docbook", "pattern": "block", "text": 12, "before": 3572, "parent": 796, "depth": 2, "xmlId": "e41" , "children": [{ "pattern": "textual", "text": 12, "before": 3572, "parent": 12, "depth": 3, "xmlId": "e41" } ] }, { "gid": "para", "ns": "http://docbook.org/ns/docbook", "pattern": "block", "text": 784, "before": 3584, "parent": 796, "depth": 2, "xmlId": "e42" , "children": [{ "pattern": "textual", "text": 350, "before": 3584, "parent": 784, "depth": 3, "xmlId": "e42" }, { "gid": "emphasis", "ns": "http://docbook.org/ns/docbook", "pattern": "inline", "text": 37, "before": 3934, "parent": 784, "depth": 3, "xmlId": "e43" , "children": [{ "pattern": "textual", "text": 37, "before": 3934, "parent": 37, "depth": 4, "xmlId": "e43" } ] }, { "pattern": "textual", "text": 397, "before": 3971, "parent": 784, "depth": 3, "xmlId": "e42" } ] } ] }, { "gid": "section", "ns": "http://docbook.org/ns/docbook", "pattern": "hcontainer", "text": 3903, "before": 4368, "parent": 17656, "depth": 1, "xmlId": "e44" , "children": [{ "gid": "title", "ns": "http://docbook.org/ns/docbook", "pattern": "block", "text": 26, "before": 4368, "parent": 3903, "depth": 2, "xmlId": "e45" , "children": [{ "pattern": "textual", "text": 26, "before": 4368, "parent": 26, "depth": 3, "xmlId": "e45" } ] }, { "gid": "para", "ns": "http://docbook.org/ns/docbook", "pattern": "block", "text": 1148, "before": 4394, "parent": 3903, "depth": 2, "xmlId": "e46" , "children": [{ "pattern": "textual", "text": 738, "before": 4394, "parent": 1148, "depth": 3, "xmlId": "e46" }, { "gid": "xref", "ns": "http://docbook.org/ns/docbook", "pattern": "milestone", "text": 100, "before": 5132, "parent": 1148, "depth": 3, "xmlId": "e47" , "children": [{ "pattern": "textual", "text": 100, "before": 5132, "parent": 100, "depth": 4, "xmlId": "e47" } ] }, { "pattern": "textual", "text": 310, "before": 5232, "parent": 1148, "depth": 3, "xmlId": "e46" } ] }, { "gid": "figure", "ns": "http://docbook.org/ns/docbook", "pattern": "container", "text": 171, "before": 5542, "parent": 3903, "depth": 2, "xmlId": "e48" , "children": [{ "gid": "title", "ns": "http://docbook.org/ns/docbook", "pattern": "block", "text": 71, "before": 5542, "parent": 171, "depth": 3, "xmlId": "e49" , "children": [{ "pattern": "textual", "text": 71, "before": 5542, "parent": 71, "depth": 4, "xmlId": "e49" } ] }, { "gid": "mediaobject", "ns": "http://docbook.org/ns/docbook", "pattern": "container", "text": 100, "before": 5613, "parent": 171, "depth": 3, "xmlId": "e50" , "children": [{ "gid": "imageobject", "ns": "http://docbook.org/ns/docbook", "pattern": "container", "text": 100, "before": 5613, "parent": 100, "depth": 4, "xmlId": "e51" , "children": [{ "gid": "imagedata", "ns": "http://docbook.org/ns/docbook", "pattern": "meta", "text": 100, "before": 5613, "parent": 100, "depth": 5, "xmlId": "e52" , "children": [{ "pattern": "textual", "text": 100, "before": 5613, "parent": 100, "depth": 6, "xmlId": "e52" } ] } ] } ] } ] }, { "gid": "para", "ns": "http://docbook.org/ns/docbook", "pattern": "block", "text": 1647, "before": 5713, "parent": 3903, "depth": 2, "xmlId": "e53" , "children": [{ "pattern": "textual", "text": 1647, "before": 5713, "parent": 1647, "depth": 3, "xmlId": "e53" } ] }, { "gid": "para", "ns": "http://docbook.org/ns/docbook", "pattern": "block", "text": 778, "before": 7360, "parent": 3903, "depth": 2, "xmlId": "e54" , "children": [{ "pattern": "textual", "text": 778, "before": 7360, "parent": 778, "depth": 3, "xmlId": "e54" } ] }, { "gid": "para", "ns": "http://docbook.org/ns/docbook", "pattern": "block", "text": 133, "before": 8138, "parent": 3903, "depth": 2, "xmlId": "e55" , "children": [{ "pattern": "textual", "text": 133, "before": 8138, "parent": 133, "depth": 3, "xmlId": "e55" } ] } ] }, { "gid": "section", "ns": "http://docbook.org/ns/docbook", "pattern": "hcontainer", "text": 8601, "before": 8271, "parent": 17656, "depth": 1, "xmlId": "e56" , "children": [{ "gid": "title", "ns": "http://docbook.org/ns/docbook", "pattern": "block", "text": 18, "before": 8271, "parent": 8601, "depth": 2, "xmlId": "e57" , "children": [{ "pattern": "textual", "text": 18, "before": 8271, "parent": 18, "depth": 3, "xmlId": "e57" } ] }, { "gid": "para", "ns": "http://docbook.org/ns/docbook", "pattern": "block", "text": 1452, "before": 8289, "parent": 8601, "depth": 2, "xmlId": "e58" , "children": [{ "pattern": "textual", "text": 589, "before": 8289, "parent": 1452, "depth": 3, "xmlId": "e58" }, { "gid": "emphasis", "ns": "http://docbook.org/ns/docbook", "pattern": "inline", "text": 6, "before": 8878, "parent": 1452, "depth": 3, "xmlId": "e59" , "children": [{ "pattern": "textual", "text": 6, "before": 8878, "parent": 6, "depth": 4, "xmlId": "e59" } ] }, { "pattern": "textual", "text": 27, "before": 8884, "parent": 1452, "depth": 3, "xmlId": "e58" }, { "gid": "footnote", "ns": "http://docbook.org/ns/docbook", "pattern": "popup", "text": 260, "before": 8911, "parent": 1452, "depth": 3, "xmlId": "e60" , "children": [{ "gid": "para", "ns": "http://docbook.org/ns/docbook", "pattern": "block", "text": 260, "before": 8911, "parent": 260, "depth": 4, "xmlId": "e61" , "children": [{ "pattern": "textual", "text": 159, "before": 8911, "parent": 260, "depth": 5, "xmlId": "e61" }, { "gid": "xref", "ns": "http://docbook.org/ns/docbook", "pattern": "milestone", "text": 100, "before": 9070, "parent": 260, "depth": 5, "xmlId": "e62" , "children": [{ "pattern": "textual", "text": 100, "before": 9070, "parent": 100, "depth": 6, "xmlId": "e62" } ] }, { "pattern": "textual", "text": 1, "before": 9170, "parent": 260, "depth": 5, "xmlId": "e61" } ] } ] }, { "pattern": "textual", "text": 55, "before": 9171, "parent": 1452, "depth": 3, "xmlId": "e58" }, { "gid": "emphasis", "ns": "http://docbook.org/ns/docbook", "pattern": "inline", "text": 21, "before": 9226, "parent": 1452, "depth": 3, "xmlId": "e63" , "children": [{ "pattern": "textual", "text": 21, "before": 9226, "parent": 21, "depth": 4, "xmlId": "e63" } ] }, { "pattern": "textual", "text": 2, "before": 9247, "parent": 1452, "depth": 3, "xmlId": "e58" }, { "gid": "emphasis", "ns": "http://docbook.org/ns/docbook", "pattern": "inline", "text": 8, "before": 9249, "parent": 1452, "depth": 3, "xmlId": "e64" , "children": [{ "pattern": "textual", "text": 8, "before": 9249, "parent": 8, "depth": 4, "xmlId": "e64" } ] }, { "pattern": "textual", "text": 2, "before": 9257, "parent": 1452, "depth": 3, "xmlId": "e58" }, { "gid": "emphasis", "ns": "http://docbook.org/ns/docbook", "pattern": "inline", "text": 33, "before": 9259, "parent": 1452, "depth": 3, "xmlId": "e65" , "children": [{ "pattern": "textual", "text": 33, "before": 9259, "parent": 33, "depth": 4, "xmlId": "e65" } ] }, { "pattern": "textual", "text": 5, "before": 9292, "parent": 1452, "depth": 3, "xmlId": "e58" }, { "gid": "emphasis", "ns": "http://docbook.org/ns/docbook", "pattern": "inline", "text": 19, "before": 9297, "parent": 1452, "depth": 3, "xmlId": "e66" , "children": [{ "pattern": "textual", "text": 19, "before": 9297, "parent": 19, "depth": 4, "xmlId": "e66" } ] }, { "pattern": "textual", "text": 48, "before": 9316, "parent": 1452, "depth": 3, "xmlId": "e58" }, { "gid": "emphasis", "ns": "http://docbook.org/ns/docbook", "pattern": "inline", "text": 3, "before": 9364, "parent": 1452, "depth": 3, "xmlId": "e67" , "children": [{ "pattern": "textual", "text": 3, "before": 9364, "parent": 3, "depth": 4, "xmlId": "e67" } ] }, { "pattern": "textual", "text": 2, "before": 9367, "parent": 1452, "depth": 3, "xmlId": "e58" }, { "gid": "emphasis", "ns": "http://docbook.org/ns/docbook", "pattern": "inline", "text": 3, "before": 9369, "parent": 1452, "depth": 3, "xmlId": "e68" , "children": [{ "pattern": "textual", "text": 3, "before": 9369, "parent": 3, "depth": 4, "xmlId": "e68" } ] }, { "pattern": "textual", "text": 2, "before": 9372, "parent": 1452, "depth": 3, "xmlId": "e58" }, { "gid": "emphasis", "ns": "http://docbook.org/ns/docbook", "pattern": "inline", "text": 5, "before": 9374, "parent": 1452, "depth": 3, "xmlId": "e69" , "children": [{ "pattern": "textual", "text": 5, "before": 9374, "parent": 5, "depth": 4, "xmlId": "e69" } ] }, { "pattern": "textual", "text": 12, "before": 9379, "parent": 1452, "depth": 3, "xmlId": "e58" }, { "gid": "emphasis", "ns": "http://docbook.org/ns/docbook", "pattern": "inline", "text": 3, "before": 9391, "parent": 1452, "depth": 3, "xmlId": "e70" , "children": [{ "pattern": "textual", "text": 3, "before": 9391, "parent": 3, "depth": 4, "xmlId": "e70" } ] }, { "pattern": "textual", "text": 48, "before": 9394, "parent": 1452, "depth": 3, "xmlId": "e58" }, { "gid": "xref", "ns": "http://docbook.org/ns/docbook", "pattern": "milestone", "text": 100, "before": 9442, "parent": 1452, "depth": 3, "xmlId": "e71" , "children": [{ "pattern": "textual", "text": 100, "before": 9442, "parent": 100, "depth": 4, "xmlId": "e71" } ] }, { "pattern": "textual", "text": 199, "before": 9542, "parent": 1452, "depth": 3, "xmlId": "e58" } ] }, { "gid": "figure", "ns": "http://docbook.org/ns/docbook", "pattern": "container", "text": 190, "before": 9741, "parent": 8601, "depth": 2, "xmlId": "e72" , "children": [{ "gid": "title", "ns": "http://docbook.org/ns/docbook", "pattern": "block", "text": 90, "before": 9741, "parent": 190, "depth": 3, "xmlId": "e73" , "children": [{ "pattern": "textual", "text": 90, "before": 9741, "parent": 90, "depth": 4, "xmlId": "e73" } ] }, { "gid": "mediaobject", "ns": "http://docbook.org/ns/docbook", "pattern": "container", "text": 100, "before": 9831, "parent": 190, "depth": 3, "xmlId": "e74" , "children": [{ "gid": "imageobject", "ns": "http://docbook.org/ns/docbook", "pattern": "container", "text": 100, "before": 9831, "parent": 100, "depth": 4, "xmlId": "e75" , "children": [{ "gid": "imagedata", "ns": "http://docbook.org/ns/docbook", "pattern": "meta", "text": 100, "before": 9831, "parent": 100, "depth": 5, "xmlId": "e76" , "children": [{ "pattern": "textual", "text": 100, "before": 9831, "parent": 100, "depth": 6, "xmlId": "e76" } ] } ] } ] } ] }, { "gid": "section", "ns": "http://docbook.org/ns/docbook", "pattern": "hcontainer", "text": 4292, "before": 9931, "parent": 8601, "depth": 2, "xmlId": "e77" , "children": [{ "gid": "title", "ns": "http://docbook.org/ns/docbook", "pattern": "block", "text": 21, "before": 9931, "parent": 4292, "depth": 3, "xmlId": "e78" , "children": [{ "pattern": "textual", "text": 21, "before": 9931, "parent": 21, "depth": 4, "xmlId": "e78" } ] }, { "gid": "para", "ns": "http://docbook.org/ns/docbook", "pattern": "block", "text": 674, "before": 9952, "parent": 4292, "depth": 3, "xmlId": "e79" , "children": [{ "pattern": "textual", "text": 526, "before": 9952, "parent": 674, "depth": 4, "xmlId": "e79" }, { "gid": "xref", "ns": "http://docbook.org/ns/docbook", "pattern": "milestone", "text": 100, "before": 10478, "parent": 674, "depth": 4, "xmlId": "e80" , "children": [{ "pattern": "textual", "text": 100, "before": 10478, "parent": 100, "depth": 5, "xmlId": "e80" } ] }, { "pattern": "textual", "text": 48, "before": 10578, "parent": 674, "depth": 4, "xmlId": "e79" } ] }, { "gid": "figure", "ns": "http://docbook.org/ns/docbook", "pattern": "container", "text": 2687, "before": 10626, "parent": 4292, "depth": 3, "xmlId": "e81" , "children": [{ "gid": "title", "ns": "http://docbook.org/ns/docbook", "pattern": "block", "text": 32, "before": 10626, "parent": 2687, "depth": 4, "xmlId": "e82" , "children": [{ "pattern": "textual", "text": 32, "before": 10626, "parent": 32, "depth": 5, "xmlId": "e82" } ] }, { "gid": "programlisting", "ns": "http://docbook.org/ns/docbook", "pattern": "block", "text": 2655, "before": 10658, "parent": 2687, "depth": 4, "xmlId": "e83" , "children": [{ "pattern": "textual", "text": 2655, "before": 10658, "parent": 2655, "depth": 5, "xmlId": "e83" } ] } ] }, { "gid": "para", "ns": "http://docbook.org/ns/docbook", "pattern": "block", "text": 910, "before": 13313, "parent": 4292, "depth": 3, "xmlId": "e84" , "children": [{ "pattern": "textual", "text": 641, "before": 13313, "parent": 910, "depth": 4, "xmlId": "e84" }, { "gid": "xref", "ns": "http://docbook.org/ns/docbook", "pattern": "milestone", "text": 100, "before": 13954, "parent": 910, "depth": 4, "xmlId": "e85" , "children": [{ "pattern": "textual", "text": 100, "before": 13954, "parent": 100, "depth": 5, "xmlId": "e85" } ] }, { "pattern": "textual", "text": 169, "before": 14054, "parent": 910, "depth": 4, "xmlId": "e84" } ] } ] }, { "gid": "section", "ns": "http://docbook.org/ns/docbook", "pattern": "hcontainer", "text": 1458, "before": 14223, "parent": 8601, "depth": 2, "xmlId": "e86" , "children": [{ "gid": "title", "ns": "http://docbook.org/ns/docbook", "pattern": "block", "text": 14, "before": 14223, "parent": 1458, "depth": 3, "xmlId": "e87" , "children": [{ "pattern": "textual", "text": 14, "before": 14223, "parent": 14, "depth": 4, "xmlId": "e87" } ] }, { "gid": "para", "ns": "http://docbook.org/ns/docbook", "pattern": "block", "text": 1444, "before": 14237, "parent": 1458, "depth": 3, "xmlId": "e88" , "children": [{ "pattern": "textual", "text": 446, "before": 14237, "parent": 1444, "depth": 4, "xmlId": "e88" }, { "gid": "xref", "ns": "http://docbook.org/ns/docbook", "pattern": "milestone", "text": 100, "before": 14683, "parent": 1444, "depth": 4, "xmlId": "e89" , "children": [{ "pattern": "textual", "text": 100, "before": 14683, "parent": 100, "depth": 5, "xmlId": "e89" } ] }, { "pattern": "textual", "text": 125, "before": 14783, "parent": 1444, "depth": 4, "xmlId": "e88" }, { "gid": "footnote", "ns": "http://docbook.org/ns/docbook", "pattern": "popup", "text": 71, "before": 14908, "parent": 1444, "depth": 4, "xmlId": "e90" , "children": [{ "gid": "para", "ns": "http://docbook.org/ns/docbook", "pattern": "block", "text": 71, "before": 14908, "parent": 71, "depth": 5, "xmlId": "e91" , "children": [{ "pattern": "textual", "text": 54, "before": 14908, "parent": 71, "depth": 6, "xmlId": "e91" }, { "gid": "link", "ns": "http://docbook.org/ns/docbook", "pattern": "inline", "text": 16, "before": 14962, "parent": 71, "depth": 6, "xmlId": "e92" , "children": [{ "pattern": "textual", "text": 16, "before": 14962, "parent": 16, "depth": 7, "xmlId": "e92" } ] }, { "pattern": "textual", "text": 1, "before": 14978, "parent": 71, "depth": 6, "xmlId": "e91" } ] } ] }, { "pattern": "textual", "text": 291, "before": 14979, "parent": 1444, "depth": 4, "xmlId": "e88" }, { "gid": "xref", "ns": "http://docbook.org/ns/docbook", "pattern": "milestone", "text": 100, "before": 15270, "parent": 1444, "depth": 4, "xmlId": "e93" , "children": [{ "pattern": "textual", "text": 100, "before": 15270, "parent": 100, "depth": 5, "xmlId": "e93" } ] }, { "pattern": "textual", "text": 197, "before": 15370, "parent": 1444, "depth": 4, "xmlId": "e88" }, { "gid": "xref", "ns": "http://docbook.org/ns/docbook", "pattern": "milestone", "text": 100, "before": 15567, "parent": 1444, "depth": 4, "xmlId": "e94" , "children": [{ "pattern": "textual", "text": 100, "before": 15567, "parent": 100, "depth": 5, "xmlId": "e94" } ] }, { "pattern": "textual", "text": 14, "before": 15667, "parent": 1444, "depth": 4, "xmlId": "e88" } ] } ] }, { "gid": "section", "ns": "http://docbook.org/ns/docbook", "pattern": "hcontainer", "text": 1191, "before": 15681, "parent": 8601, "depth": 2, "xmlId": "e95" , "children": [{ "gid": "title", "ns": "http://docbook.org/ns/docbook", "pattern": "block", "text": 29, "before": 15681, "parent": 1191, "depth": 3, "xmlId": "e96" , "children": [{ "pattern": "textual", "text": 29, "before": 15681, "parent": 29, "depth": 4, "xmlId": "e96" } ] }, { "gid": "para", "ns": "http://docbook.org/ns/docbook", "pattern": "block", "text": 1162, "before": 15710, "parent": 1191, "depth": 3, "xmlId": "e97" , "children": [{ "pattern": "textual", "text": 1113, "before": 15710, "parent": 1162, "depth": 4, "xmlId": "e97" }, { "gid": "link", "ns": "http://docbook.org/ns/docbook", "pattern": "inline", "text": 48, "before": 16823, "parent": 1162, "depth": 4, "xmlId": "e98" , "children": [{ "pattern": "textual", "text": 48, "before": 16823, "parent": 48, "depth": 5, "xmlId": "e98" } ] }, { "pattern": "textual", "text": 1, "before": 16871, "parent": 1162, "depth": 4, "xmlId": "e97" } ] } ] } ] }, { "gid": "bibliography", "ns": "http://docbook.org/ns/docbook", "pattern": "hcontainer", "text": 784, "before": 16872, "parent": 17656, "depth": 1, "xmlId": "e99" , "children": [{ "gid": "title", "ns": "http://docbook.org/ns/docbook", "pattern": "block", "text": 10, "before": 16872, "parent": 784, "depth": 2, "xmlId": "e100" , "children": [{ "pattern": "textual", "text": 10, "before": 16872, "parent": 10, "depth": 3, "xmlId": "e100" } ] }, { "gid": "bibliomixed", "ns": "http://docbook.org/ns/docbook", "pattern": "block", "text": 157, "before": 16882, "parent": 784, "depth": 2, "xmlId": "e101" , "children": [{ "pattern": "textual", "text": 157, "before": 16882, "parent": 157, "depth": 3, "xmlId": "e101" } ] }, { "gid": "bibliomixed", "ns": "http://docbook.org/ns/docbook", "pattern": "block", "text": 281, "before": 17039, "parent": 784, "depth": 2, "xmlId": "e102" , "children": [{ "pattern": "textual", "text": 251, "before": 17039, "parent": 281, "depth": 3, "xmlId": "e102" }, { "gid": "biblioid", "ns": "http://docbook.org/ns/docbook", "pattern": "atom", "text": 29, "before": 17290, "parent": 281, "depth": 3, "xmlId": "e103" , "children": [{ "pattern": "textual", "text": 29, "before": 17290, "parent": 29, "depth": 4, "xmlId": "e103" } ] }, { "pattern": "textual", "text": 1, "before": 17319, "parent": 281, "depth": 3, "xmlId": "e102" } ] }, { "gid": "bibliomixed", "ns": "http://docbook.org/ns/docbook", "pattern": "block", "text": 336, "before": 17320, "parent": 784, "depth": 2, "xmlId": "e104" , "children": [{ "pattern": "textual", "text": 336, "before": 17320, "parent": 336, "depth": 3, "xmlId": "e104" } ] } ] } ] }  ]
